napari_tabu/__init__.py
napari_tabu/_dock_widget.py
napari_tabu/_function.py
napari_tabu/_tests/__init__.py
napari_tabu/_tests/test_dock_widget.py
napari_tabu/_tests/test_function.py
napari_tabu-0.1.5.dist-info/LICENSE
napari_tabu-0.1.5.dist-info/METADATA
napari_tabu-0.1.5.dist-info/WHEEL
napari_tabu-0.1.5.dist-info/entry_points.txt
napari_tabu-0.1.5.dist-info/top_level.txt
napari_tabu-0.1.5.dist-info/RECORD
